destinelab/__init__.py
destinelab/climate_dt_dictionary.py
destinelab/de_token.py
destinelab/dedl_auth.py
destinelab/desp_auth.py
destinelab/extreme_dt_dictionary.py
destinelab_test-0.2.0.dist-info/METADATA
destinelab_test-0.2.0.dist-info/WHEEL
destinelab_test-0.2.0.dist-info/top_level.txt
destinelab_test-0.2.0.dist-info/RECORD
