Metadata-Version: 2.1
Name: destinelab_test
Version: 0.2.0
Requires-Dist: requests
Requires-Dist: lxml
Requires-Dist: PyJWT
